skcomm/__init__.py
skcomm/channel.py
skcomm/filters.py
skcomm/instrument_control.py
skcomm/pre_distortion.py
skcomm/rx.py
skcomm/signal.py
skcomm/tx.py
skcomm/utils.py
skcomm/visualizer.py
skcomm/cython_mods/rx_cython.c
skcomm/cython_mods/rx_cython.cp311-win_amd64.pyd
skcomm/cython_mods/rx_cython.pyx
skcomm/cython_mods/setup_rx_cython.py
skcomm/tests/__init__.py
skcomm/tests/test_channel.py
skcomm/tests/test_filters.py
skcomm/tests/test_rx.py
skcomm/tests/test_rx_cython.py
skcomm/tests/test_tx.py
skcomm/tests/test_utils.py
scikit_comm-0.0.6.dist-info/LICENSE.txt
scikit_comm-0.0.6.dist-info/METADATA
scikit_comm-0.0.6.dist-info/WHEEL
scikit_comm-0.0.6.dist-info/top_level.txt
scikit_comm-0.0.6.dist-info/RECORD
