Metadata-Version: 2.2
Name: scikit-comm
Version: 0.0.6
Summary: Routines to simulate communication systems
Author-email: Markus Nölle <noelle@htw-berlin.de>
Project-URL: Homepage, https://gitlab.com/htw-ikt-noelle/scikit-comm
Project-URL: Documentation, https://scikit-comm.readthedocs.io/en/latest/
Project-URL: Bug Tracker, https://gitlab.com/htw-ikt-noelle/scikit-comm/-/issues
Classifier: Programming Language :: Python :: 3
Requires-Python: >=3.11
License-File: LICENSE.txt
Requires-Dist: matplotlib
Requires-Dist: numpy
Requires-Dist: PyVISA
Requires-Dist: PyVISA-py
Requires-Dist: scipy
Requires-Dist: screeninfo
